setup.py
ddvc_distributions/Binomialdistribution.py
ddvc_distributions/Gaussiandistribution.py
ddvc_distributions/Generaldistribution.py
ddvc_distributions/__init__.py
ddvc_distributions.egg-info/PKG-INFO
ddvc_distributions.egg-info/SOURCES.txt
ddvc_distributions.egg-info/dependency_links.txt
ddvc_distributions.egg-info/not-zip-safe
ddvc_distributions.egg-info/top_level.txt