Metadata-Version: 1.0
Name: ddvc-distributions
Version: 1.0
Summary:  Package to calculate and plot Gaussian and Binomial distribution
Home-page: UNKNOWN
Author: David De Vargas
Author-email: dvccueter@gmail.com
License: UNKNOWN
Platform: UNKNOWN
